moleditpy/__init__.py
moleditpy/__main__.py
moleditpy/main.py
moleditpy/modules/__init__.py
moleditpy/modules/about_dialog.py
moleditpy/modules/align_plane_dialog.py
moleditpy/modules/alignment_dialog.py
moleditpy/modules/analysis_window.py
moleditpy/modules/angle_dialog.py
moleditpy/modules/atom_item.py
moleditpy/modules/bond_item.py
moleditpy/modules/bond_length_dialog.py
moleditpy/modules/calculation_worker.py
moleditpy/modules/color_settings_dialog.py
moleditpy/modules/constants.py
moleditpy/modules/constrained_optimization_dialog.py
moleditpy/modules/custom_interactor_style.py
moleditpy/modules/custom_qt_interactor.py
moleditpy/modules/dialog3_d_picking_mixin.py
moleditpy/modules/dihedral_dialog.py
moleditpy/modules/main_window.py
moleditpy/modules/main_window_app_state.py
moleditpy/modules/main_window_compute.py
moleditpy/modules/main_window_dialog_manager.py
moleditpy/modules/main_window_edit_3d.py
moleditpy/modules/main_window_edit_actions.py
moleditpy/modules/main_window_export.py
moleditpy/modules/main_window_main_init.py
moleditpy/modules/main_window_molecular_parsers.py
moleditpy/modules/main_window_project_io.py
moleditpy/modules/main_window_string_importers.py
moleditpy/modules/main_window_ui_manager.py
moleditpy/modules/main_window_view_3d.py
moleditpy/modules/main_window_view_loaders.py
moleditpy/modules/mirror_dialog.py
moleditpy/modules/molecular_data.py
moleditpy/modules/molecule_scene.py
moleditpy/modules/move_group_dialog.py
moleditpy/modules/periodic_table_dialog.py
moleditpy/modules/planarize_dialog.py
moleditpy/modules/plugin_interface.py
moleditpy/modules/plugin_manager.py
moleditpy/modules/plugin_manager_window.py
moleditpy/modules/settings_dialog.py
moleditpy/modules/template_preview_item.py
moleditpy/modules/template_preview_view.py
moleditpy/modules/translation_dialog.py
moleditpy/modules/user_template_dialog.py
moleditpy/modules/zoomable_view.py
moleditpy/modules/assets/icon.icns
moleditpy/modules/assets/icon.ico
moleditpy-2.2.4.dist-info/licenses/LICENSE
moleditpy-2.2.4.dist-info/METADATA
moleditpy-2.2.4.dist-info/WHEEL
moleditpy-2.2.4.dist-info/entry_points.txt
moleditpy-2.2.4.dist-info/top_level.txt
moleditpy-2.2.4.dist-info/RECORD
