Metadata-Version: 2.4
Name: MoleditPy
Version: 2.2.4
Summary: A cross-platform, simple, and intuitive molecular structure editor built in Python. It allows 2D molecular drawing and 3D structure visualization. It supports exporting structure files for input to DFT calculation software.
Author-email: HiroYokoyama <titech.yoko.hiro@gmail.com>
License:                     GNU GENERAL PUBLIC LICENSE
Project-URL: Homepage, https://github.com/HiroYokoyama/python_molecular_editor
Project-URL: Issues, https://github.com/HiroYokoyama/python_molecular_editor/issues
Classifier: Programming Language :: Python :: 3
Classifier: Operating System :: OS Independent
Classifier: Intended Audience :: Science/Research
Classifier: Topic :: Scientific/Engineering :: Chemistry
Classifier: Programming Language :: Python :: 3.9
Classifier: Programming Language :: Python :: 3.10
Classifier: Programming Language :: Python :: 3.11
Classifier: Programming Language :: Python :: 3.12
Classifier: Programming Language :: Python :: 3.13
Requires-Python: <3.14,>=3.9
License-File: LICENSE
Requires-Dist: numpy
Requires-Dist: pyqt6<6.10
Requires-Dist: pyvista<0.47
Requires-Dist: pyvistaqt<0.12
Requires-Dist: rdkit<2025.10
Requires-Dist: openbabel-wheel<3.2
Dynamic: license-file
